pronoundb/__init__.py
pronoundb/client.py
pronoundb/platform.py
pronoundb/pronoun_response.py
pronoundb/translations.py
pronoundb-3.0.1.dist-info/LICENSE
pronoundb-3.0.1.dist-info/METADATA
pronoundb-3.0.1.dist-info/WHEEL
pronoundb-3.0.1.dist-info/RECORD
