Metadata-Version: 2.1
Name: pronoundb
Version: 3.0.1
Summary: API wrapper for the pronoundb.org API.
Home-page: https://git.steffo.dev/SteffoSpieler/python-pronoundb-lib
License: MIT
Keywords: pronouns,pronoundb,api
Author: SteffoSpieler
Author-email: steffo@steffospieler.de
Maintainer: SteffoSpieler
Maintainer-email: steffo@steffospieler.de
Requires-Python: >=3.9,<4.0
Classifier: License :: OSI Approved :: MIT License
Classifier: Programming Language :: Python :: 3
Classifier: Programming Language :: Python :: 3.9
Classifier: Programming Language :: Python :: 3.10
Classifier: Programming Language :: Python :: 3.11
Classifier: Programming Language :: Python :: 3.12
Requires-Dist: aiohttp (>=3.9,<4.0)
Project-URL: Repository, https://git.steffo.dev/SteffoSpieler/python-pronoundb-lib
